{"macro_topic": "History", "topic": "History Workflow Series (\"World Wide Web\")", "worker": "2022_7", "goals": {"1": "Find the inventors of World Wide Web (return IRI and name).", "2": "Identify the BGP for hypertext system.", "3": "Find all the hypertext systems born before the 1980 (return the IRI and name of the system and the inception date).", "4": "Identify the BGP for computer scientist", "5": "Find how many computer scientists there are for each continent (consider their citizenship). Return the IRI and name of the continent and the number of scientists for each continent.", "6": "Find all the computer scientists who thaught at the University of Cambridge (return IRI and name)", "7": "Find all the computer scientists who wrote at least 5 books (please consider only the instances of book, exclude \"literary work\" or other type of work related to books). Return the IRI and name of the computer scientist and the number of books."}, "name": "e49c8d021d", "search_workflow": {"1": [{"narrative": "retrieve all properties of World Wide Web", "query": "SELECT DISTINCT ?p ?name WHERE { wd:Q466 ?p ?obj . ?p sc:name ?name. }", "output": [[["p", "http://www.wikidata.org/prop/direct/P1051"], ["name", "PSH ID"]], [["p", "http://www.wikidata.org/prop/direct/P1225"], ["name", "U.S. National Archives Identifier"]], [["p", "http://www.wikidata.org/prop/direct/P1417"], ["name", "Encyclop\u00e6dia Britannica Online ID"]], [["p", "http://www.wikidata.org/prop/direct/P1430"], ["name", "OpenPlaques subject ID"]], [["p", "http://www.wikidata.org/prop/direct/P1482"], ["name", "Stack Exchange tag"]], [["p", "http://www.wikidata.org/prop/direct/P1542"], ["name", "has effect"]], [["p", "http://www.wikidata.org/prop/direct/P1813"], ["name", "short name"]], [["p", "http://www.wikidata.org/prop/direct/P1889"], ["name", "different from"]], [["p", "http://www.wikidata.org/prop/direct/P2004"], ["name", "NALT ID"]], [["p", "http://www.wikidata.org/prop/direct/P2163"], ["name", "FAST ID"]], [["p", "http://www.wikidata.org/prop/direct/P2184"], ["name", "history of topic"]], [["p", "http://www.wikidata.org/prop/direct/P227"], ["name", "GND ID"]], [["p", "http://www.wikidata.org/prop/direct/P2347"], ["name", "YSO ID"]], [["p", "http://www.wikidata.org/prop/direct/P244"], ["name", "Library of Congress authority ID"]], [["p", "http://www.wikidata.org/prop/direct/P2581"], ["name", "BabelNet ID"]], [["p", "http://www.wikidata.org/prop/direct/P2612"], ["name", "TED topic ID"]], [["p", "http://www.wikidata.org/prop/direct/P268"], ["name", "Biblioth\u00e8que nationale de France ID"]], [["p", "http://www.wikidata.org/prop/direct/P279"], ["name", "subclass of"]], [["p", "http://www.wikidata.org/prop/direct/P2959"], ["name", "permanent duplicated item"]], [["p", "http://www.wikidata.org/prop/direct/P31"], ["name", "instance of"]], [["p", "http://www.wikidata.org/prop/direct/P3222"], ["name", "NE.se ID"]], [["p", "http://www.wikidata.org/prop/direct/P3381"], ["name", "File Format Wiki page ID"]], [["p", "http://www.wikidata.org/prop/direct/P3417"], ["name", "Quora topic ID"]], [["p", "http://www.wikidata.org/prop/direct/P3553"], ["name", "Zhihu topic ID"]], [["p", "http://www.wikidata.org/prop/direct/P373"], ["name", "Commons category"]], [["p", "http://www.wikidata.org/prop/direct/P3827"], ["name", "JSTOR topic ID"]], [["p", "http://www.wikidata.org/prop/direct/P3847"], ["name", "Open Library subject ID"]], [["p", "http://www.wikidata.org/prop/direct/P4342"], ["name", "Store norske leksikon ID"]], [["p", "http://www.wikidata.org/prop/direct/P5008"], ["name", "on focus list of Wikimedia project"]], [["p", "http://www.wikidata.org/prop/direct/P5019"], ["name", "Brockhaus Enzyklop\u00e4die online ID"]], [["p", "http://www.wikidata.org/prop/direct/P508"], ["name", "BNCF Thesaurus ID"]], [["p", "http://www.wikidata.org/prop/direct/P527"], ["name", "has part"]], [["p", "http://www.wikidata.org/prop/direct/P5398"], ["name", "TDKIV term ID"]], [["p", "http://www.wikidata.org/prop/direct/P571"], ["name", "inception"]], [["p", "http://www.wikidata.org/prop/direct/P575"], ["name", "time of discovery or invention"]], [["p", "http://www.wikidata.org/prop/direct/P61"], ["name", "discoverer or inventor"]], [["p", "http://www.wikidata.org/prop/direct/P6366"], ["name", "Microsoft Academic ID"]], [["p", "http://www.wikidata.org/prop/direct/P646"], ["name", "Freebase ID"]], [["p", "http://www.wikidata.org/prop/direct/P6611"], ["name", "Semantic Scholar topic ID"]], [["p", "http://www.wikidata.org/prop/direct/P7033"], ["name", "Australian Educational Vocabulary ID"]], [["p", "http://www.wikidata.org/prop/direct/P737"], ["name", "influenced by"]], [["p", "http://www.wikidata.org/prop/direct/P7818"], ["name", "French Vikidia ID"]], [["p", "http://www.wikidata.org/prop/direct/P793"], ["name", "significant event"]], [["p", "http://www.wikidata.org/prop/direct/P8408"], ["name", "KBpedia ID"]], [["p", "http://www.wikidata.org/prop/direct/P910"], ["name", "topic's main category"]], [["p", "http://www.wikidata.org/prop/direct/P935"], ["name", "Commons gallery"]], [["p", "http://www.wikidata.org/prop/direct/P950"], ["name", "Biblioteca Nacional de Espa\u00f1a ID"]], [["p", "http://www.wikidata.org/prop/direct/P2179"], ["name", "ACM Classification Code (2012)"]], [["p", "http://www.wikidata.org/prop/direct/P3893"], ["name", "public domain date"]]], "parseError": null, "execution": [{"datetime": "20/Dec/2022:19:14:55"}], "keywords": {"SELECT": 1, "ASK": 0, "DESCRIBE": 0, "CONSTRUCT": 0, "NESTED QUERY": 0, "DISTINCT": 1, "LIMIT": 0, "OFFSET": 0, "ORDER BY": 0, "FILTER": 0, "REGEX": 0, "AND": 0, "UNION": 0, "OPT": 0, "GRAPH": 0, "EXISTS": 0, "NOT EXISTS": 0, "MINUS": 0, "COUNT": 0, "MAX": 0, "MIN": 0, "AVG": 0, "SUM": 0, "GROUP BY": 0, "HAVING": 0, "GROUP_CONCAT": 0}, "index": 0, "recall": 0.0, "precision": 0.0, "accuracy": 0.0, "fscore": 0.0}, {"narrative": "from the previous query we obtain [('p', 'http://www.wikidata.org/prop/direct/P61'), ('name', 'discoverer or inventor')]\nlet's use the property P61 to retrieve the inventors of 'World Wide Web'", "query": "SELECT DISTINCT ?obj ?name WHERE { wd:Q466 wdt:P61 ?obj. ?obj sc:name ?name. } LIMIT 20", "output": [[["obj", "http://www.wikidata.org/entity/Q80"], ["name", "Tim Berners-Lee"]], [["obj", "http://www.wikidata.org/entity/Q92749"], ["name", "Robert Cailliau"]]], "parseError": null, "execution": [{"datetime": "20/Dec/2022:19:16:47"}], "keywords": {"SELECT": 1, "ASK": 0, "DESCRIBE": 0, "CONSTRUCT": 0, "NESTED QUERY": 0, "DISTINCT": 1, "LIMIT": 1, "OFFSET": 0, "ORDER BY": 0, "FILTER": 0, "REGEX": 0, "AND": 0, "UNION": 0, "OPT": 0, "GRAPH": 0, "EXISTS": 0, "NOT EXISTS": 0, "MINUS": 0, "COUNT": 0, "MAX": 0, "MIN": 0, "AVG": 0, "SUM": 0, "GROUP BY": 0, "HAVING": 0, "GROUP_CONCAT": 0}, "index": 1, "recall": 1.0, "precision": 1.0, "accuracy": 0.0, "fscore": 1.0}], "2": [{"narrative": "", "query": "SELECT DISTINCT ?obj ?name WHERE { wd:Q466 wdt:P31 ?obj. ?obj sc:name ?name. } LIMIT 20", "output": [[["obj", "http://www.wikidata.org/entity/Q121182"], ["name", "information system"]], [["obj", "http://www.wikidata.org/entity/Q65966993"], ["name", "hypertext system"]]], "parseError": null, "execution": [{"datetime": "20/Dec/2022:19:17:36"}, {"datetime": "20/Dec/2022:19:18:04"}], "keywords": {"SELECT": 1, "ASK": 0, "DESCRIBE": 0, "CONSTRUCT": 0, "NESTED QUERY": 0, "DISTINCT": 1, "LIMIT": 1, "OFFSET": 0, "ORDER BY": 0, "FILTER": 0, "REGEX": 0, "AND": 0, "UNION": 0, "OPT": 0, "GRAPH": 0, "EXISTS": 0, "NOT EXISTS": 0, "MINUS": 0, "COUNT": 0, "MAX": 0, "MIN": 0, "AVG": 0, "SUM": 0, "GROUP BY": 0, "HAVING": 0, "GROUP_CONCAT": 0}, "index": 0, "recall": 1.0, "precision": 0.5, "accuracy": 0.0, "fscore": 0.6666666666666666}], "3": [{"narrative": "[('obj', 'http://www.wikidata.org/entity/Q65966993'), ('name', 'hypertext system')]\nfirst of all let's get all the hypertext systems in the database", "query": "SELECT DISTINCT ?obj ?name WHERE { ?obj wdt:P31 wd:Q65966993. ?obj sc:name ?name. }", "output": [[["obj", "http://www.wikidata.org/entity/Q466"], ["name", "World Wide Web"]], [["obj", "http://www.wikidata.org/entity/Q370979"], ["name", "Amigaguide"]], [["obj", "http://www.wikidata.org/entity/Q2385520"], ["name", "ENQUIRE"]], [["obj", "http://www.wikidata.org/entity/Q4994212"], ["name", "Hypertext Editing System"]], [["obj", "http://www.wikidata.org/entity/Q5448331"], ["name", "File Retrieval and Editing System"]], [["obj", "http://www.wikidata.org/entity/Q785345"], ["name", "Project Xanadu"]], [["obj", "http://www.wikidata.org/entity/Q1799609"], ["name", "HyTime"]], [["obj", "http://www.wikidata.org/entity/Q7742259"], ["name", "The Interactive Encyclopedia System"]], [["obj", "http://www.wikidata.org/entity/Q74587961"], ["name", "MaxThink"]], [["obj", "http://www.wikidata.org/entity/Q74590695"], ["name", "HyperRez"]], [["obj", "http://www.wikidata.org/entity/Q74667091"], ["name", "HOUDINI"]], [["obj", "http://www.wikidata.org/entity/Q66561170"], ["name", "Visual Knowledge Builder"]], [["obj", "http://www.wikidata.org/entity/Q66561696"], ["name", "VIKI"]], [["obj", "http://www.wikidata.org/entity/Q1166919"], ["name", "Darwin Information Typing Architecture"]], [["obj", "http://www.wikidata.org/entity/Q1053749"], ["name", "HyperCard"]], [["obj", "http://www.wikidata.org/entity/Q74679064"], ["name", "TransText"]], [["obj", "http://www.wikidata.org/entity/Q94638515"], ["name", "Gemini"]], [["obj", "http://www.wikidata.org/entity/Q2442968"], ["name", "ToolBook"]], [["obj", "http://www.wikidata.org/entity/Q2367048"], ["name", "SuperCard"]], [["obj", "http://www.wikidata.org/entity/Q5319181"], ["name", "Dynatext"]], [["obj", "http://www.wikidata.org/entity/Q73516071"], ["name", "Andrew Toolkit"]], [["obj", "http://www.wikidata.org/entity/Q5964462"], ["name", "Knowledge Management System"]], [["obj", "http://www.wikidata.org/entity/Q67170587"], ["name", "Expeditee"]], [["obj", "http://www.wikidata.org/entity/Q67147168"], ["name", "Macweb"]], [["obj", "http://www.wikidata.org/entity/Q73916721"], ["name", "HyperWriter!"]], [["obj", "http://www.wikidata.org/entity/Q15411624"], ["name", "Twine"]], [["obj", "http://www.wikidata.org/entity/Q6839396"], ["name", "Microcosm"]], [["obj", "http://www.wikidata.org/entity/Q471"], ["name", "Memex"]], [["obj", "http://www.wikidata.org/entity/Q2583312"], ["name", "WinPlus"]], [["obj", "http://www.wikidata.org/entity/Q73664535"], ["name", "Folio Views"]], [["obj", "http://www.wikidata.org/entity/Q66124479"], ["name", "Hyper-G"]], [["obj", "http://www.wikidata.org/entity/Q75004603"], ["name", "IBM LinkWay"]], [["obj", "http://www.wikidata.org/entity/Q1050365"], ["name", "oNLine System"]], [["obj", "http://www.wikidata.org/entity/Q8063246"], ["name", "ZOG"]], [["obj", "http://www.wikidata.org/entity/Q66916307"], ["name", "token_word"]], [["obj", "http://www.wikidata.org/entity/Q3625272"], ["name", "Aspen Movie Map"]], [["obj", "http://www.wikidata.org/entity/Q5358242"], ["name", "Electronic Document System"]], [["obj", "http://www.wikidata.org/entity/Q11153199"], ["name", "Intermedia"]], [["obj", "http://www.wikidata.org/entity/Q7620478"], ["name", "Storyspace"]], [["obj", "http://www.wikidata.org/entity/Q380574"], ["name", "Knowledge Navigator"]], [["obj", "http://www.wikidata.org/entity/Q5615425"], ["name", "Guide"]], [["obj", "http://www.wikidata.org/entity/Q11793087"], ["name", "NoteCards"]], [["obj", "http://www.wikidata.org/entity/Q74428178"], ["name", "HyperCOSTOC"]], [["obj", "http://www.wikidata.org/entity/Q66125212"], ["name", "Konstanz Hypertext System"]], [["obj", "http://www.wikidata.org/entity/Q74670748"], ["name", "PC-Hypertext"]], [["obj", "http://www.wikidata.org/entity/Q63079762"], ["name", "OpenXanadu"]], [["obj", "http://www.wikidata.org/entity/Q66821230"], ["name", "Sun's Link Service"]], [["obj", "http://www.wikidata.org/entity/Q73737542"], ["name", "HyperPAD"]], [["obj", "http://www.wikidata.org/entity/Q104714171"], ["name", "HM-Card"]], [["obj", "http://www.wikidata.org/entity/Q7060634"], ["name", "Norton Guides"]], [["obj", "http://www.wikidata.org/entity/Q7661194"], ["name", "Symbolics Document Examiner"]], [["obj", "http://www.wikidata.org/entity/Q74588296"], ["name", "Hyplus"]], [["obj", "http://www.wikidata.org/entity/Q67168848"], ["name", "Udanax Green"]]], "parseError": null, "execution": [{"datetime": "20/Dec/2022:19:19:29"}, {"datetime": "20/Dec/2022:19:19:51"}, {"datetime": "20/Dec/2022:19:20:42"}, {"datetime": "20/Dec/2022:19:21:42"}], "keywords": {"SELECT": 1, "ASK": 0, "DESCRIBE": 0, "CONSTRUCT": 0, "NESTED QUERY": 0, "DISTINCT": 1, "LIMIT": 0, "OFFSET": 0, "ORDER BY": 0, "FILTER": 0, "REGEX": 0, "AND": 0, "UNION": 0, "OPT": 0, "GRAPH": 0, "EXISTS": 0, "NOT EXISTS": 0, "MINUS": 0, "COUNT": 0, "MAX": 0, "MIN": 0, "AVG": 0, "SUM": 0, "GROUP BY": 0, "HAVING": 0, "GROUP_CONCAT": 0}, "index": 0, "recall": 1.0, "precision": 0.16981132075471697, "accuracy": 0.0, "fscore": 0.2903225806451613}, {"narrative": "let's look at a generic 'hypertext systems' properties and try to find something like date of creation", "query": "SELECT DISTINCT ?p ?name WHERE { wd:Q466 ?p ?obj. ?p sc:name ?name. }", "output": [[["p", "http://www.wikidata.org/prop/direct/P1051"], ["name", "PSH ID"]], [["p", "http://www.wikidata.org/prop/direct/P1225"], ["name", "U.S. National Archives Identifier"]], [["p", "http://www.wikidata.org/prop/direct/P1417"], ["name", "Encyclop\u00e6dia Britannica Online ID"]], [["p", "http://www.wikidata.org/prop/direct/P1430"], ["name", "OpenPlaques subject ID"]], [["p", "http://www.wikidata.org/prop/direct/P1482"], ["name", "Stack Exchange tag"]], [["p", "http://www.wikidata.org/prop/direct/P1542"], ["name", "has effect"]], [["p", "http://www.wikidata.org/prop/direct/P1813"], ["name", "short name"]], [["p", "http://www.wikidata.org/prop/direct/P1889"], ["name", "different from"]], [["p", "http://www.wikidata.org/prop/direct/P2004"], ["name", "NALT ID"]], [["p", "http://www.wikidata.org/prop/direct/P2163"], ["name", "FAST ID"]], [["p", "http://www.wikidata.org/prop/direct/P2184"], ["name", "history of topic"]], [["p", "http://www.wikidata.org/prop/direct/P227"], ["name", "GND ID"]], [["p", "http://www.wikidata.org/prop/direct/P2347"], ["name", "YSO ID"]], [["p", "http://www.wikidata.org/prop/direct/P244"], ["name", "Library of Congress authority ID"]], [["p", "http://www.wikidata.org/prop/direct/P2581"], ["name", "BabelNet ID"]], [["p", "http://www.wikidata.org/prop/direct/P2612"], ["name", "TED topic ID"]], [["p", "http://www.wikidata.org/prop/direct/P268"], ["name", "Biblioth\u00e8que nationale de France ID"]], [["p", "http://www.wikidata.org/prop/direct/P279"], ["name", "subclass of"]], [["p", "http://www.wikidata.org/prop/direct/P2959"], ["name", "permanent duplicated item"]], [["p", "http://www.wikidata.org/prop/direct/P31"], ["name", "instance of"]], [["p", "http://www.wikidata.org/prop/direct/P3222"], ["name", "NE.se ID"]], [["p", "http://www.wikidata.org/prop/direct/P3381"], ["name", "File Format Wiki page ID"]], [["p", "http://www.wikidata.org/prop/direct/P3417"], ["name", "Quora topic ID"]], [["p", "http://www.wikidata.org/prop/direct/P3553"], ["name", "Zhihu topic ID"]], [["p", "http://www.wikidata.org/prop/direct/P373"], ["name", "Commons category"]], [["p", "http://www.wikidata.org/prop/direct/P3827"], ["name", "JSTOR topic ID"]], [["p", "http://www.wikidata.org/prop/direct/P3847"], ["name", "Open Library subject ID"]], [["p", "http://www.wikidata.org/prop/direct/P4342"], ["name", "Store norske leksikon ID"]], [["p", "http://www.wikidata.org/prop/direct/P5008"], ["name", "on focus list of Wikimedia project"]], [["p", "http://www.wikidata.org/prop/direct/P5019"], ["name", "Brockhaus Enzyklop\u00e4die online ID"]], [["p", "http://www.wikidata.org/prop/direct/P508"], ["name", "BNCF Thesaurus ID"]], [["p", "http://www.wikidata.org/prop/direct/P527"], ["name", "has part"]], [["p", "http://www.wikidata.org/prop/direct/P5398"], ["name", "TDKIV term ID"]], [["p", "http://www.wikidata.org/prop/direct/P571"], ["name", "inception"]], [["p", "http://www.wikidata.org/prop/direct/P575"], ["name", "time of discovery or invention"]], [["p", "http://www.wikidata.org/prop/direct/P61"], ["name", "discoverer or inventor"]], [["p", "http://www.wikidata.org/prop/direct/P6366"], ["name", "Microsoft Academic ID"]], [["p", "http://www.wikidata.org/prop/direct/P646"], ["name", "Freebase ID"]], [["p", "http://www.wikidata.org/prop/direct/P6611"], ["name", "Semantic Scholar topic ID"]], [["p", "http://www.wikidata.org/prop/direct/P7033"], ["name", "Australian Educational Vocabulary ID"]], [["p", "http://www.wikidata.org/prop/direct/P737"], ["name", "influenced by"]], [["p", "http://www.wikidata.org/prop/direct/P7818"], ["name", "French Vikidia ID"]], [["p", "http://www.wikidata.org/prop/direct/P793"], ["name", "significant event"]], [["p", "http://www.wikidata.org/prop/direct/P8408"], ["name", "KBpedia ID"]], [["p", "http://www.wikidata.org/prop/direct/P910"], ["name", "topic's main category"]], [["p", "http://www.wikidata.org/prop/direct/P935"], ["name", "Commons gallery"]], [["p", "http://www.wikidata.org/prop/direct/P950"], ["name", "Biblioteca Nacional de Espa\u00f1a ID"]], [["p", "http://www.wikidata.org/prop/direct/P2179"], ["name", "ACM Classification Code (2012)"]], [["p", "http://www.wikidata.org/prop/direct/P3893"], ["name", "public domain date"]]], "parseError": null, "execution": [{"datetime": "20/Dec/2022:19:24:12"}], "keywords": {"SELECT": 1, "ASK": 0, "DESCRIBE": 0, "CONSTRUCT": 0, "NESTED QUERY": 0, "DISTINCT": 1, "LIMIT": 0, "OFFSET": 0, "ORDER BY": 0, "FILTER": 0, "REGEX": 0, "AND": 0, "UNION": 0, "OPT": 0, "GRAPH": 0, "EXISTS": 0, "NOT EXISTS": 0, "MINUS": 0, "COUNT": 0, "MAX": 0, "MIN": 0, "AVG": 0, "SUM": 0, "GROUP BY": 0, "HAVING": 0, "GROUP_CONCAT": 0}, "index": 1, "recall": 0.0, "precision": 0.0, "accuracy": 0.0, "fscore": 0.0}, {"narrative": "[('p', 'http://www.wikidata.org/prop/direct/P575'), ('name', 'time of discovery or invention')]\nlet's try to get hypertext systems and their date of invention", "query": "SELECT DISTINCT ?obj ?name ?date WHERE { ?obj wdt:P31 wd:Q65966993; wdt:P575 ?date. ?obj sc:name ?name. }", "output": [[["obj", "http://www.wikidata.org/entity/Q466"], ["name", "World Wide Web"], ["date", "1990-01-01T00:00:00Z"]]], "parseError": null, "execution": [{"datetime": "20/Dec/2022:19:26:43"}], "keywords": {"SELECT": 1, "ASK": 0, "DESCRIBE": 0, "CONSTRUCT": 0, "NESTED QUERY": 0, "DISTINCT": 1, "LIMIT": 0, "OFFSET": 0, "ORDER BY": 0, "FILTER": 0, "REGEX": 0, "AND": 0, "UNION": 0, "OPT": 0, "GRAPH": 0, "EXISTS": 0, "NOT EXISTS": 0, "MINUS": 0, "COUNT": 0, "MAX": 0, "MIN": 0, "AVG": 0, "SUM": 0, "GROUP BY": 0, "HAVING": 0, "GROUP_CONCAT": 0}, "index": 2, "recall": 0.0, "precision": 0.0, "accuracy": 0.0, "fscore": 0.0}, {"narrative": "[('p', 'http://www.wikidata.org/prop/direct/P575'), ('name', 'time of discovery or invention')] is not correct, let's look for a different property\n[('p', 'http://www.wikidata.org/prop/direct/P571'), ('name', 'inception')]\nlet's try to get hypertext systems and their date of invention", "query": "SELECT DISTINCT ?obj ?name ?date WHERE { ?obj wdt:P31 wd:Q65966993; wdt:P571 ?date. ?obj sc:name ?name. }", "output": [[["obj", "http://www.wikidata.org/entity/Q466"], ["name", "World Wide Web"], ["date", "1989-03-12T00:00:00Z"]], [["obj", "http://www.wikidata.org/entity/Q466"], ["name", "World Wide Web"], ["date", "1990-12-01T00:00:00Z"]], [["obj", "http://www.wikidata.org/entity/Q370979"], ["name", "Amigaguide"], ["date", "1991-01-01T00:00:00Z"]], [["obj", "http://www.wikidata.org/entity/Q2385520"], ["name", "ENQUIRE"], ["date", "1980-01-01T00:00:00Z"]], [["obj", "http://www.wikidata.org/entity/Q2385520"], ["name", "ENQUIRE"], ["date", "1984-01-01T00:00:00Z"]], [["obj", "http://www.wikidata.org/entity/Q4994212"], ["name", "Hypertext Editing System"], ["date", "1967-01-01T00:00:00Z"]], [["obj", "http://www.wikidata.org/entity/Q5448331"], ["name", "File Retrieval and Editing System"], ["date", "1968-01-01T00:00:00Z"]], [["obj", "http://www.wikidata.org/entity/Q785345"], ["name", "Project Xanadu"], ["date", "1960-01-01T00:00:00Z"]], [["obj", "http://www.wikidata.org/entity/Q1799609"], ["name", "HyTime"], ["date", "1992-01-01T00:00:00Z"]], [["obj", "http://www.wikidata.org/entity/Q7742259"], ["name", "The Interactive Encyclopedia System"], ["date", "1983-01-01T00:00:00Z"]], [["obj", "http://www.wikidata.org/entity/Q66561170"], ["name", "Visual Knowledge Builder"], ["date", "2001-01-01T00:00:00Z"]], [["obj", "http://www.wikidata.org/entity/Q66561696"], ["name", "VIKI"], ["date", "1994-01-01T00:00:00Z"]], [["obj", "http://www.wikidata.org/entity/Q1166919"], ["name", "Darwin Information Typing Architecture"], ["date", "2001-01-01T00:00:00Z"]], [["obj", "http://www.wikidata.org/entity/Q1053749"], ["name", "HyperCard"], ["date", "1987-01-01T00:00:00Z"]], [["obj", "http://www.wikidata.org/entity/Q94638515"], ["name", "Gemini"], ["date", "2019-06-20T00:00:00Z"]], [["obj", "http://www.wikidata.org/entity/Q5319181"], ["name", "Dynatext"], ["date", "1990-01-01T00:00:00Z"]], [["obj", "http://www.wikidata.org/entity/Q73516071"], ["name", "Andrew Toolkit"], ["date", "1988-01-01T00:00:00Z"]], [["obj", "http://www.wikidata.org/entity/Q67170587"], ["name", "Expeditee"], ["date", "2006-01-01T00:00:00Z"]], [["obj", "http://www.wikidata.org/entity/Q15411624"], ["name", "Twine"], ["date", "2009-01-01T00:00:00Z"]], [["obj", "http://www.wikidata.org/entity/Q6839396"], ["name", "Microcosm"], ["date", "1988-01-01T00:00:00Z"]], [["obj", "http://www.wikidata.org/entity/Q471"], ["name", "Memex"], ["date", "1939-01-01T00:00:00Z"]], [["obj", "http://www.wikidata.org/entity/Q75004603"], ["name", "IBM LinkWay"], ["date", "1987-01-01T00:00:00Z"]], [["obj", "http://www.wikidata.org/entity/Q1050365"], ["name", "oNLine System"], ["date", "1962-01-01T00:00:00Z"]], [["obj", "http://www.wikidata.org/entity/Q8063246"], ["name", "ZOG"], ["date", "1977-01-01T00:00:00Z"]], [["obj", "http://www.wikidata.org/entity/Q3625272"], ["name", "Aspen Movie Map"], ["date", "1978-01-01T00:00:00Z"]], [["obj", "http://www.wikidata.org/entity/Q5358242"], ["name", "Electronic Document System"], ["date", "1978-01-01T00:00:00Z"]], [["obj", "http://www.wikidata.org/entity/Q7620478"], ["name", "Storyspace"], ["date", "1985-01-01T00:00:00Z"]], [["obj", "http://www.wikidata.org/entity/Q5615425"], ["name", "Guide"], ["date", "1982-01-01T00:00:00Z"]], [["obj", "http://www.wikidata.org/entity/Q11793087"], ["name", "NoteCards"], ["date", "1984-01-01T00:00:00Z"]], [["obj", "http://www.wikidata.org/entity/Q74428178"], ["name", "HyperCOSTOC"], ["date", "1989-01-01T00:00:00Z"]], [["obj", "http://www.wikidata.org/entity/Q104714171"], ["name", "HM-Card"], ["date", "1995-01-01T00:00:00Z"]], [["obj", "http://www.wikidata.org/entity/Q7060634"], ["name", "Norton Guides"], ["date", "1985-01-01T00:00:00Z"]]], "parseError": null, "execution": [{"datetime": "20/Dec/2022:19:28:36"}, {"datetime": "20/Dec/2022:19:30:30"}], "keywords": {"SELECT": 1, "ASK": 0, "DESCRIBE": 0, "CONSTRUCT": 0, "NESTED QUERY": 0, "DISTINCT": 1, "LIMIT": 0, "OFFSET": 0, "ORDER BY": 0, "FILTER": 0, "REGEX": 0, "AND": 0, "UNION": 0, "OPT": 0, "GRAPH": 0, "EXISTS": 0, "NOT EXISTS": 0, "MINUS": 0, "COUNT": 0, "MAX": 0, "MIN": 0, "AVG": 0, "SUM": 0, "GROUP BY": 0, "HAVING": 0, "GROUP_CONCAT": 0}, "index": 3, "recall": 1.0, "precision": 0.28125, "accuracy": 1.0, "fscore": 0.43902439024390244}, {"narrative": "using the property inception we are able to get all hypertext systems and their date of invention\nthe next step is to filter and find all the hypertext systems born before the 1980 (return the IRI and name of the system and the inception date).", "query": "SELECT DISTINCT ?obj ?name ?date WHERE { ?obj wdt:P31 wd:Q65966993; wdt:P571 ?date. ?obj sc:name ?name. FILTER (?date < \"1980\"^^xsd:gYear). }", "output": [[["obj", "http://www.wikidata.org/entity/Q2385520"], ["name", "ENQUIRE"], ["date", "1980-01-01T00:00:00Z"]], [["obj", "http://www.wikidata.org/entity/Q4994212"], ["name", "Hypertext Editing System"], ["date", "1967-01-01T00:00:00Z"]], [["obj", "http://www.wikidata.org/entity/Q5448331"], ["name", "File Retrieval and Editing System"], ["date", "1968-01-01T00:00:00Z"]], [["obj", "http://www.wikidata.org/entity/Q785345"], ["name", "Project Xanadu"], ["date", "1960-01-01T00:00:00Z"]], [["obj", "http://www.wikidata.org/entity/Q471"], ["name", "Memex"], ["date", "1939-01-01T00:00:00Z"]], [["obj", "http://www.wikidata.org/entity/Q1050365"], ["name", "oNLine System"], ["date", "1962-01-01T00:00:00Z"]], [["obj", "http://www.wikidata.org/entity/Q8063246"], ["name", "ZOG"], ["date", "1977-01-01T00:00:00Z"]], [["obj", "http://www.wikidata.org/entity/Q3625272"], ["name", "Aspen Movie Map"], ["date", "1978-01-01T00:00:00Z"]], [["obj", "http://www.wikidata.org/entity/Q5358242"], ["name", "Electronic Document System"], ["date", "1978-01-01T00:00:00Z"]]], "parseError": null, "execution": [{"datetime": "20/Dec/2022:19:31:47"}, {"datetime": "20/Dec/2022:19:32:06"}], "keywords": {"SELECT": 1, "ASK": 0, "DESCRIBE": 0, "CONSTRUCT": 0, "NESTED QUERY": 0, "DISTINCT": 1, "LIMIT": 0, "OFFSET": 0, "ORDER BY": 0, "FILTER": 1, "REGEX": 0, "AND": 0, "UNION": 0, "OPT": 0, "GRAPH": 0, "EXISTS": 0, "NOT EXISTS": 0, "MINUS": 0, "COUNT": 0, "MAX": 0, "MIN": 0, "AVG": 0, "SUM": 0, "GROUP BY": 0, "HAVING": 0, "GROUP_CONCAT": 0}, "index": 4, "recall": 1.0, "precision": 1.0, "accuracy": 1.0, "fscore": 1.0}], "4": [{"narrative": "let's try to find the BGP for computer scientist using the entity associated to Tim Berners-Lee, inventor of the World Wide Web\nreturn all the profession of Tim Berners-Lee (Q80)", "query": "SELECT DISTINCT ?obj ?name WHERE { wd:Q80 wdt:P106 ?obj. ?obj sc:name ?name. }", "output": [[["obj", "http://www.wikidata.org/entity/Q1622272"], ["name", "university teacher"]], [["obj", "http://www.wikidata.org/entity/Q169470"], ["name", "physicist"]], [["obj", "http://www.wikidata.org/entity/Q205375"], ["name", "inventor"]], [["obj", "http://www.wikidata.org/entity/Q81096"], ["name", "engineer"]], [["obj", "http://www.wikidata.org/entity/Q82594"], ["name", "computer scientist"]], [["obj", "http://www.wikidata.org/entity/Q5482740"], ["name", "programmer"]], [["obj", "http://www.wikidata.org/entity/Q6859454"], ["name", "web developer"]]], "parseError": null, "execution": [{"datetime": "20/Dec/2022:19:34:03"}], "keywords": {"SELECT": 1, "ASK": 0, "DESCRIBE": 0, "CONSTRUCT": 0, "NESTED QUERY": 0, "DISTINCT": 1, "LIMIT": 0, "OFFSET": 0, "ORDER BY": 0, "FILTER": 0, "REGEX": 0, "AND": 0, "UNION": 0, "OPT": 0, "GRAPH": 0, "EXISTS": 0, "NOT EXISTS": 0, "MINUS": 0, "COUNT": 0, "MAX": 0, "MIN": 0, "AVG": 0, "SUM": 0, "GROUP BY": 0, "HAVING": 0, "GROUP_CONCAT": 0}, "index": 0, "recall": 1.0, "precision": 0.14285714285714285, "accuracy": 0.0, "fscore": 0.25}], "5": [{"narrative": "[('obj', 'http://www.wikidata.org/entity/Q82594'), ('name', 'computer scientist')]\nfirst of all let's get all the computer scientists in the world", "query": "SELECT DISTINCT ?computer_scientist ?name WHERE { ?computer_scientist wdt:P31 wd:Q5; wdt:P106 wd:Q82594. ?computer_scientist sc:name ?name. } LIMIT 20", "output": [[["computer_scientist", "http://www.wikidata.org/entity/Q8190500"], ["name", "Seinosuke Toda"]], [["computer_scientist", "http://www.wikidata.org/entity/Q603999"], ["name", "Kevin Poulsen"]], [["computer_scientist", "http://www.wikidata.org/entity/Q11109023"], ["name", "Michael Barr"]], [["computer_scientist", "http://www.wikidata.org/entity/Q20731777"], ["name", "Valeria de Paiva"]], [["computer_scientist", "http://www.wikidata.org/entity/Q24901829"], ["name", "Ernesto Damiani"]], [["computer_scientist", "http://www.wikidata.org/entity/Q61856956"], ["name", "Richard Garner"]], [["computer_scientist", "http://www.wikidata.org/entity/Q6539960"], ["name", "Liang-Jie Zhang"]], [["computer_scientist", "http://www.wikidata.org/entity/Q92669"], ["name", "Jeffrey Shallit"]], [["computer_scientist", "http://www.wikidata.org/entity/Q15842362"], ["name", "Richard Clippinger"]], [["computer_scientist", "http://www.wikidata.org/entity/Q15858435"], ["name", "Hardo Bourguignon"]], [["computer_scientist", "http://www.wikidata.org/entity/Q15917430"], ["name", "A. Ollongren"]], [["computer_scientist", "http://www.wikidata.org/entity/Q16018928"], ["name", "Jim Thomas"]], [["computer_scientist", "http://www.wikidata.org/entity/Q241735"], ["name", "Robert Noyce"]], [["computer_scientist", "http://www.wikidata.org/entity/Q7312654"], ["name", "Renato M. E. Sabbatini"]], [["computer_scientist", "http://www.wikidata.org/entity/Q16174254"], ["name", "Drude Berntsen"]], [["computer_scientist", "http://www.wikidata.org/entity/Q16186703"], ["name", "Timothy J. Hickey"]], [["computer_scientist", "http://www.wikidata.org/entity/Q16193458"], ["name", "Terry Myerson"]], [["computer_scientist", "http://www.wikidata.org/entity/Q16194868"], ["name", "Ross Williams"]], [["computer_scientist", "http://www.wikidata.org/entity/Q16195136"], ["name", "Frans Kaashoek"]], [["computer_scientist", "http://www.wikidata.org/entity/Q16195669"], ["name", "William Martens"]]], "parseError": null, "execution": [{"datetime": "20/Dec/2022:20:54:48"}, {"datetime": "20/Dec/2022:20:57:23"}, {"datetime": "20/Dec/2022:21:16:04"}, {"datetime": "20/Dec/2022:21:40:41"}], "keywords": {"SELECT": 1, "ASK": 0, "DESCRIBE": 0, "CONSTRUCT": 0, "NESTED QUERY": 0, "DISTINCT": 1, "LIMIT": 1, "OFFSET": 0, "ORDER BY": 0, "FILTER": 0, "REGEX": 0, "AND": 0, "UNION": 0, "OPT": 0, "GRAPH": 0, "EXISTS": 0, "NOT EXISTS": 0, "MINUS": 0, "COUNT": 0, "MAX": 0, "MIN": 0, "AVG": 0, "SUM": 0, "GROUP BY": 0, "HAVING": 0, "GROUP_CONCAT": 0}, "index": 0, "recall": 0.0, "precision": 0.0, "accuracy": 0.0, "fscore": 0.0}, {"narrative": "let's look at a generic computer scientist properties to find out if there is a citizenship property", "query": "SELECT DISTINCT ?p ?name WHERE { wd:Q8190500 ?p ?obj. ?p sc:name ?name. } LIMIT 20", "output": [[["p", "http://www.wikidata.org/prop/direct/P106"], ["name", "occupation"]], [["p", "http://www.wikidata.org/prop/direct/P108"], ["name", "employer"]], [["p", "http://www.wikidata.org/prop/direct/P166"], ["name", "award received"]], [["p", "http://www.wikidata.org/prop/direct/P1814"], ["name", "name in kana"]], [["p", "http://www.wikidata.org/prop/direct/P184"], ["name", "doctoral advisor"]], [["p", "http://www.wikidata.org/prop/direct/P19"], ["name", "place of birth"]], [["p", "http://www.wikidata.org/prop/direct/P21"], ["name", "sex or gender"]], [["p", "http://www.wikidata.org/prop/direct/P213"], ["name", "ISNI"]], [["p", "http://www.wikidata.org/prop/direct/P214"], ["name", "VIAF ID"]], [["p", "http://www.wikidata.org/prop/direct/P2456"], ["name", "DBLP author ID"]], [["p", "http://www.wikidata.org/prop/direct/P27"], ["name", "country of citizenship"]], [["p", "http://www.wikidata.org/prop/direct/P31"], ["name", "instance of"]], [["p", "http://www.wikidata.org/prop/direct/P349"], ["name", "National Diet Library ID"]], [["p", "http://www.wikidata.org/prop/direct/P4955"], ["name", "MR Author ID"]], [["p", "http://www.wikidata.org/prop/direct/P549"], ["name", "Mathematics Genealogy Project ID"]], [["p", "http://www.wikidata.org/prop/direct/P551"], ["name", "residence"]], [["p", "http://www.wikidata.org/prop/direct/P569"], ["name", "date of birth"]], [["p", "http://www.wikidata.org/prop/direct/P646"], ["name", "Freebase ID"]], [["p", "http://www.wikidata.org/prop/direct/P69"], ["name", "educated at"]], [["p", "http://www.wikidata.org/prop/direct/P7859"], ["name", "WorldCat Identities ID"]]], "parseError": null, "execution": [{"datetime": "20/Dec/2022:21:16:42"}, {"datetime": "20/Dec/2022:21:20:37"}, {"datetime": "20/Dec/2022:21:43:04"}, {"datetime": "20/Dec/2022:21:44:17"}], "keywords": {"SELECT": 1, "ASK": 0, "DESCRIBE": 0, "CONSTRUCT": 0, "NESTED QUERY": 0, "DISTINCT": 1, "LIMIT": 1, "OFFSET": 0, "ORDER BY": 0, "FILTER": 0, "REGEX": 0, "AND": 0, "UNION": 0, "OPT": 0, "GRAPH": 0, "EXISTS": 0, "NOT EXISTS": 0, "MINUS": 0, "COUNT": 0, "MAX": 0, "MIN": 0, "AVG": 0, "SUM": 0, "GROUP BY": 0, "HAVING": 0, "GROUP_CONCAT": 0}, "index": 1, "recall": 0.0, "precision": 0.0, "accuracy": 0.0, "fscore": 0.0}, {"narrative": "[('p', 'http://www.wikidata.org/prop/direct/P27'), ('name', 'country of citizenship')]\nlet's get all the computer scientists in the world with their nationality", "query": "SELECT DISTINCT ?computer_scientist ?name ?nation WHERE { ?computer_scientist wdt:P31 wd:Q5; wdt:P106 wd:Q82594; wdt:P27 ?nationality. ?computer_scientist sc:name ?name. ?nationality sc:name ?nation. } LIMIT 20", "output": [[["computer_scientist", "http://www.wikidata.org/entity/Q3018520"], ["name", "David Naccache"], ["nation", "Morocco"]], [["computer_scientist", "http://www.wikidata.org/entity/Q1045568"], ["name", "Carsten Haitzler"], ["nation", "Nigeria"]], [["computer_scientist", "http://www.wikidata.org/entity/Q28648829"], ["name", "Clarisse Iribagiza"], ["nation", "Rwanda"]], [["computer_scientist", "http://www.wikidata.org/entity/Q26207354"], ["name", "Lum Zhaveli"], ["nation", "Kosovo"]], [["computer_scientist", "http://www.wikidata.org/entity/Q24565815"], ["name", "Narasimhiah Seshagiri"], ["nation", "British India"]], [["computer_scientist", "http://www.wikidata.org/entity/Q253960"], ["name", "Ravi Sethi"], ["nation", "British India"]], [["computer_scientist", "http://www.wikidata.org/entity/Q21715732"], ["name", "Syed Jan Abas"], ["nation", "British India"]], [["computer_scientist", "http://www.wikidata.org/entity/Q53977158"], ["name", "Svetlana Selezneva"], ["nation", "Ukrainian Soviet Socialist Republic"]], [["computer_scientist", "http://www.wikidata.org/entity/Q92987"], ["name", "Wang Xuan"], ["nation", "Republic of China 1912\u20131949"]], [["computer_scientist", "http://www.wikidata.org/entity/Q1045031"], ["name", "Liu Chuanzhi"], ["nation", "Republic of China 1912\u20131949"]], [["computer_scientist", "http://www.wikidata.org/entity/Q41390"], ["name", "Kurt G\u00f6del"], ["nation", "First Czechoslovak Republic"]], [["computer_scientist", "http://www.wikidata.org/entity/Q17496977"], ["name", "Michel Robert"], ["nation", "France"]], [["computer_scientist", "http://www.wikidata.org/entity/Q92946"], ["name", "Bertrand Meyer"], ["nation", "France"]], [["computer_scientist", "http://www.wikidata.org/entity/Q24939958"], ["name", "Francis Bach"], ["nation", "France"]], [["computer_scientist", "http://www.wikidata.org/entity/Q61090466"], ["name", "Anne Siegel"], ["nation", "France"]], [["computer_scientist", "http://www.wikidata.org/entity/Q3638303"], ["name", "Beno\u00eet Minisini"], ["nation", "France"]], [["computer_scientist", "http://www.wikidata.org/entity/Q2755388"], ["name", "Philippe Dreyfus"], ["nation", "France"]], [["computer_scientist", "http://www.wikidata.org/entity/Q28477239"], ["name", "Nathalie Lauraine-Boulyguina"], ["nation", "France"]], [["computer_scientist", "http://www.wikidata.org/entity/Q92635"], ["name", "Jacques Vall\u00e9e"], ["nation", "France"]], [["computer_scientist", "http://www.wikidata.org/entity/Q93027"], ["name", "Henri Gouraud"], ["nation", "France"]]], "parseError": null, "execution": [{"datetime": "20/Dec/2022:20:59:14"}, {"datetime": "20/Dec/2022:20:59:35"}, {"datetime": "20/Dec/2022:21:03:23"}], "keywords": {"SELECT": 1, "ASK": 0, "DESCRIBE": 0, "CONSTRUCT": 0, "NESTED QUERY": 0, "DISTINCT": 1, "LIMIT": 1, "OFFSET": 0, "ORDER BY": 0, "FILTER": 0, "REGEX": 0, "AND": 0, "UNION": 0, "OPT": 0, "GRAPH": 0, "EXISTS": 0, "NOT EXISTS": 0, "MINUS": 0, "COUNT": 0, "MAX": 0, "MIN": 0, "AVG": 0, "SUM": 0, "GROUP BY": 0, "HAVING": 0, "GROUP_CONCAT": 0}, "index": 2, "recall": 0.0, "precision": 0.0, "accuracy": 0.0, "fscore": 0.0}, {"narrative": "let's get a generic country in order to have a look at its property", "query": "SELECT DISTINCT ?nationality ?nation WHERE { ?computer_scientist wdt:P31 wd:Q5; wdt:P106 wd:Q82594; wdt:P27 ?nationality. ?nationality sc:name ?nation. } LIMIT 20", "output": [[["nationality", "http://www.wikidata.org/entity/Q1028"], ["nation", "Morocco"]], [["nationality", "http://www.wikidata.org/entity/Q1033"], ["nation", "Nigeria"]], [["nationality", "http://www.wikidata.org/entity/Q1037"], ["nation", "Rwanda"]], [["nationality", "http://www.wikidata.org/entity/Q1246"], ["nation", "Kosovo"]], [["nationality", "http://www.wikidata.org/entity/Q129286"], ["nation", "British India"]], [["nationality", "http://www.wikidata.org/entity/Q133356"], ["nation", "Ukrainian Soviet Socialist Republic"]], [["nationality", "http://www.wikidata.org/entity/Q13426199"], ["nation", "Republic of China 1912\u20131949"]], [["nationality", "http://www.wikidata.org/entity/Q140359"], ["nation", "First Czechoslovak Republic"]], [["nationality", "http://www.wikidata.org/entity/Q142"], ["nation", "France"]], [["nationality", "http://www.wikidata.org/entity/Q145"], ["nation", "United Kingdom"]], [["nationality", "http://www.wikidata.org/entity/Q148"], ["nation", "People's Republic of China"]], [["nationality", "http://www.wikidata.org/entity/Q15180"], ["nation", "Soviet Union"]], [["nationality", "http://www.wikidata.org/entity/Q155"], ["nation", "Brazil"]], [["nationality", "http://www.wikidata.org/entity/Q159"], ["nation", "Russia"]], [["nationality", "http://www.wikidata.org/entity/Q16"], ["nation", "Canada"]], [["nationality", "http://www.wikidata.org/entity/Q16957"], ["nation", "German Democratic Republic"]], [["nationality", "http://www.wikidata.org/entity/Q17"], ["nation", "Japan"]], [["nationality", "http://www.wikidata.org/entity/Q172579"], ["nation", "Kingdom of Italy"]], [["nationality", "http://www.wikidata.org/entity/Q174193"], ["nation", "United Kingdom of Great Britain and Ireland"]], [["nationality", "http://www.wikidata.org/entity/Q1775277"], ["nation", "Dominion of India"]]], "parseError": null, "execution": [{"datetime": "20/Dec/2022:21:07:33"}], "keywords": {"SELECT": 1, "ASK": 0, "DESCRIBE": 0, "CONSTRUCT": 0, "NESTED QUERY": 0, "DISTINCT": 1, "LIMIT": 1, "OFFSET": 0, "ORDER BY": 0, "FILTER": 0, "REGEX": 0, "AND": 0, "UNION": 0, "OPT": 0, "GRAPH": 0, "EXISTS": 0, "NOT EXISTS": 0, "MINUS": 0, "COUNT": 0, "MAX": 0, "MIN": 0, "AVG": 0, "SUM": 0, "GROUP BY": 0, "HAVING": 0, "GROUP_CONCAT": 0}, "index": 3, "recall": 0.0, "precision": 0.0, "accuracy": 0.0, "fscore": 0.0}, {"narrative": "let's get the property to retrieve the continent from a country", "query": "SELECT DISTINCT ?p ?name WHERE { wd:Q1028 ?p ?obj. ?p sc:name ?name. } LIMIT 20", "output": [[["p", "http://www.wikidata.org/prop/direct/P1036"], ["name", "Dewey Decimal Classification"]], [["p", "http://www.wikidata.org/prop/direct/P1081"], ["name", "Human Development Index"]], [["p", "http://www.wikidata.org/prop/direct/P1082"], ["name", "population"]], [["p", "http://www.wikidata.org/prop/direct/P1151"], ["name", "topic's main Wikimedia portal"]], [["p", "http://www.wikidata.org/prop/direct/P1198"], ["name", "unemployment rate"]], [["p", "http://www.wikidata.org/prop/direct/P122"], ["name", "basic form of government"]], [["p", "http://www.wikidata.org/prop/direct/P1225"], ["name", "U.S. National Archives Identifier"]], [["p", "http://www.wikidata.org/prop/direct/P1245"], ["name", "OmegaWiki Defined Meaning"]], [["p", "http://www.wikidata.org/prop/direct/P1296"], ["name", "Gran Enciclop\u00e8dia Catalana ID"]], [["p", "http://www.wikidata.org/prop/direct/P1304"], ["name", "central bank"]], [["p", "http://www.wikidata.org/prop/direct/P1313"], ["name", "office held by head of government"]], [["p", "http://www.wikidata.org/prop/direct/P1343"], ["name", "described by source"]], [["p", "http://www.wikidata.org/prop/direct/P138"], ["name", "named after"]], [["p", "http://www.wikidata.org/prop/direct/P1417"], ["name", "Encyclop\u00e6dia Britannica Online ID"]], [["p", "http://www.wikidata.org/prop/direct/P1438"], ["name", "Jewish Encyclopedia ID (Russian)"]], [["p", "http://www.wikidata.org/prop/direct/P1448"], ["name", "official name"]], [["p", "http://www.wikidata.org/prop/direct/P1464"], ["name", "category for people born here"]], [["p", "http://www.wikidata.org/prop/direct/P1465"], ["name", "category for people who died here"]], [["p", "http://www.wikidata.org/prop/direct/P150"], ["name", "contains administrative territorial entity"]], [["p", "http://www.wikidata.org/prop/direct/P1549"], ["name", "demonym"]]], "parseError": null, "execution": [{"datetime": "20/Dec/2022:21:04:33"}, {"datetime": "20/Dec/2022:21:06:03"}], "keywords": {"SELECT": 1, "ASK": 0, "DESCRIBE": 0, "CONSTRUCT": 0, "NESTED QUERY": 0, "DISTINCT": 1, "LIMIT": 1, "OFFSET": 0, "ORDER BY": 0, "FILTER": 0, "REGEX": 0, "AND": 0, "UNION": 0, "OPT": 0, "GRAPH": 0, "EXISTS": 0, "NOT EXISTS": 0, "MINUS": 0, "COUNT": 0, "MAX": 0, "MIN": 0, "AVG": 0, "SUM": 0, "GROUP BY": 0, "HAVING": 0, "GROUP_CONCAT": 0}, "index": 4, "recall": 0.0, "precision": 0.0, "accuracy": 0.0, "fscore": 0.0}, {"narrative": "[('p', 'http://www.wikidata.org/prop/direct/P30'), ('name', 'continent')]\nReturn the IRI and name of the country and the number of scientists for each country", "query": "SELECT DISTINCT ?country ?nation COUNT (?nation) as ?number_of_scientist WHERE { ?computer_scientist wdt:P31 wd:Q5; wdt:P106 wd:Q82594; wdt:P27 ?country. ?country sc:name ?nation. } LIMIT 20", "output": [[["country", "http://www.wikidata.org/entity/Q191"], ["nation", "Estonia"], ["number_of_scientist", "53"]], [["country", "http://www.wikidata.org/entity/Q219060"], ["nation", "State of Palestine"], ["number_of_scientist", "1"]], [["country", "http://www.wikidata.org/entity/Q668"], ["nation", "India"], ["number_of_scientist", "107"]], [["country", "http://www.wikidata.org/entity/Q1036"], ["nation", "Uganda"], ["number_of_scientist", "4"]], [["country", "http://www.wikidata.org/entity/Q713750"], ["nation", "West Germany"], ["number_of_scientist", "2"]], [["country", "http://www.wikidata.org/entity/Q189"], ["nation", "Iceland"], ["number_of_scientist", "7"]], [["country", "http://www.wikidata.org/entity/Q399"], ["nation", "Armenia"], ["number_of_scientist", "3"]], [["country", "http://www.wikidata.org/entity/Q186320"], ["nation", "Grand Duchy of Baden"], ["number_of_scientist", "1"]], [["country", "http://www.wikidata.org/entity/Q1009"], ["nation", "Cameroon"], ["number_of_scientist", "5"]], [["country", "http://www.wikidata.org/entity/Q902"], ["nation", "Bangladesh"], ["number_of_scientist", "2"]], [["country", "http://www.wikidata.org/entity/Q13426199"], ["nation", "Republic of China 1912\u20131949"], ["number_of_scientist", "7"]], [["country", "http://www.wikidata.org/entity/Q159"], ["nation", "Russia"], ["number_of_scientist", "104"]], [["country", "http://www.wikidata.org/entity/Q184"], ["nation", "Belarus"], ["number_of_scientist", "8"]], [["country", "http://www.wikidata.org/entity/Q211"], ["nation", "Latvia"], ["number_of_scientist", "13"]], [["country", "http://www.wikidata.org/entity/Q664"], ["nation", "New Zealand"], ["number_of_scientist", "33"]], [["country", "http://www.wikidata.org/entity/Q801"], ["nation", "Israel"], ["number_of_scientist", "145"]], [["country", "http://www.wikidata.org/entity/Q843"], ["nation", "Pakistan"], ["number_of_scientist", "11"]], [["country", "http://www.wikidata.org/entity/Q865"], ["nation", "Taiwan"], ["number_of_scientist", "26"]], [["country", "http://www.wikidata.org/entity/Q739"], ["nation", "Colombia"], ["number_of_scientist", "4"]], [["country", "http://www.wikidata.org/entity/Q45"], ["nation", "Portugal"], ["number_of_scientist", "14"]]], "parseError": null, "execution": [{"datetime": "20/Dec/2022:21:13:37"}, {"datetime": "20/Dec/2022:21:14:23"}], "keywords": {"SELECT": 1, "ASK": 0, "DESCRIBE": 0, "CONSTRUCT": 0, "NESTED QUERY": 0, "DISTINCT": 1, "LIMIT": 1, "OFFSET": 0, "ORDER BY": 0, "FILTER": 0, "REGEX": 0, "AND": 0, "UNION": 0, "OPT": 0, "GRAPH": 0, "EXISTS": 0, "NOT EXISTS": 0, "MINUS": 0, "COUNT": 1, "MAX": 0, "MIN": 0, "AVG": 0, "SUM": 0, "GROUP BY": 0, "HAVING": 0, "GROUP_CONCAT": 0}, "index": 5, "recall": 0.0, "precision": 0.0, "accuracy": 0.0, "fscore": 0.0}, {"narrative": "Return the IRI and name of the continent and the number of scientists for each continent", "query": "SELECT DISTINCT ?continent ?name COUNT (?continent) as ?number_of_scientist WHERE { ?computer_scientist wdt:P31 wd:Q5; wdt:P106 wd:Q82594; wdt:P27 ?country. ?country wdt:P30 ?continent. ?continent sc:name ?name. } LIMIT 20", "output": [[["continent", "http://www.wikidata.org/entity/Q5401"], ["name", "Eurasia"], ["number_of_scientist", "23"]], [["continent", "http://www.wikidata.org/entity/Q46"], ["name", "Europe"], ["number_of_scientist", "3487"]], [["continent", "http://www.wikidata.org/entity/Q538"], ["name", "Insular Oceania"], ["number_of_scientist", "2479"]], [["continent", "http://www.wikidata.org/entity/Q15"], ["name", "Africa"], ["number_of_scientist", "76"]], [["continent", "http://www.wikidata.org/entity/Q18"], ["name", "South America"], ["number_of_scientist", "92"]], [["continent", "http://www.wikidata.org/entity/Q48"], ["name", "Asia"], ["number_of_scientist", "953"]], [["continent", "http://www.wikidata.org/entity/Q49"], ["name", "North America"], ["number_of_scientist", "2782"]]], "parseError": null, "execution": [{"datetime": "20/Dec/2022:21:14:45"}], "keywords": {"SELECT": 1, "ASK": 0, "DESCRIBE": 0, "CONSTRUCT": 0, "NESTED QUERY": 0, "DISTINCT": 1, "LIMIT": 1, "OFFSET": 0, "ORDER BY": 0, "FILTER": 0, "REGEX": 0, "AND": 0, "UNION": 0, "OPT": 0, "GRAPH": 0, "EXISTS": 0, "NOT EXISTS": 0, "MINUS": 0, "COUNT": 1, "MAX": 0, "MIN": 0, "AVG": 0, "SUM": 0, "GROUP BY": 0, "HAVING": 0, "GROUP_CONCAT": 0}, "index": 6, "recall": 1.0, "precision": 1.0, "accuracy": 0.2857142857142857, "fscore": 1.0}], "6": [{"narrative": "let's get the old query that gets all the computer scientists", "query": "SELECT DISTINCT ?computer_scientist ?name WHERE { ?computer_scientist wdt:P31 wd:Q5; wdt:P106 wd:Q82594. ?computer_scientist sc:name ?name. } LIMIT 20", "output": [[["computer_scientist", "http://www.wikidata.org/entity/Q8190500"], ["name", "Seinosuke Toda"]], [["computer_scientist", "http://www.wikidata.org/entity/Q603999"], ["name", "Kevin Poulsen"]], [["computer_scientist", "http://www.wikidata.org/entity/Q11109023"], ["name", "Michael Barr"]], [["computer_scientist", "http://www.wikidata.org/entity/Q20731777"], ["name", "Valeria de Paiva"]], [["computer_scientist", "http://www.wikidata.org/entity/Q24901829"], ["name", "Ernesto Damiani"]], [["computer_scientist", "http://www.wikidata.org/entity/Q61856956"], ["name", "Richard Garner"]], [["computer_scientist", "http://www.wikidata.org/entity/Q6539960"], ["name", "Liang-Jie Zhang"]], [["computer_scientist", "http://www.wikidata.org/entity/Q92669"], ["name", "Jeffrey Shallit"]], [["computer_scientist", "http://www.wikidata.org/entity/Q15842362"], ["name", "Richard Clippinger"]], [["computer_scientist", "http://www.wikidata.org/entity/Q15858435"], ["name", "Hardo Bourguignon"]], [["computer_scientist", "http://www.wikidata.org/entity/Q15917430"], ["name", "A. Ollongren"]], [["computer_scientist", "http://www.wikidata.org/entity/Q16018928"], ["name", "Jim Thomas"]], [["computer_scientist", "http://www.wikidata.org/entity/Q241735"], ["name", "Robert Noyce"]], [["computer_scientist", "http://www.wikidata.org/entity/Q7312654"], ["name", "Renato M. E. Sabbatini"]], [["computer_scientist", "http://www.wikidata.org/entity/Q16174254"], ["name", "Drude Berntsen"]], [["computer_scientist", "http://www.wikidata.org/entity/Q16186703"], ["name", "Timothy J. Hickey"]], [["computer_scientist", "http://www.wikidata.org/entity/Q16193458"], ["name", "Terry Myerson"]], [["computer_scientist", "http://www.wikidata.org/entity/Q16194868"], ["name", "Ross Williams"]], [["computer_scientist", "http://www.wikidata.org/entity/Q16195136"], ["name", "Frans Kaashoek"]], [["computer_scientist", "http://www.wikidata.org/entity/Q16195669"], ["name", "William Martens"]]], "parseError": null, "execution": [{"datetime": "20/Dec/2022:20:54:48"}, {"datetime": "20/Dec/2022:20:57:23"}, {"datetime": "20/Dec/2022:21:16:04"}, {"datetime": "20/Dec/2022:21:40:41"}], "keywords": {"SELECT": 1, "ASK": 0, "DESCRIBE": 0, "CONSTRUCT": 0, "NESTED QUERY": 0, "DISTINCT": 1, "LIMIT": 1, "OFFSET": 0, "ORDER BY": 0, "FILTER": 0, "REGEX": 0, "AND": 0, "UNION": 0, "OPT": 0, "GRAPH": 0, "EXISTS": 0, "NOT EXISTS": 0, "MINUS": 0, "COUNT": 0, "MAX": 0, "MIN": 0, "AVG": 0, "SUM": 0, "GROUP BY": 0, "HAVING": 0, "GROUP_CONCAT": 0}, "index": 0, "recall": 0.0, "precision": 0.0, "accuracy": 0.0, "fscore": 0.0}, {"narrative": "let's run a query to find the cambridge university entity", "query": "SELECT DISTINCT ?obj ?uni WHERE { ?computer_scientist wdt:P31 wd:Q5; wdt:P106 wd:Q82594; wdt:P108 ?obj. ?obj sc:name ?uni. } LIMIT 20", "output": [[["obj", "http://www.wikidata.org/entity/Q5500827"], ["uni", "Freedom of the Press Foundation"]], [["obj", "http://www.wikidata.org/entity/Q1381966"], ["uni", "Flipkart"]], [["obj", "http://www.wikidata.org/entity/Q2119882"], ["uni", "Google Nest"]], [["obj", "http://www.wikidata.org/entity/Q4863446"], ["uni", "Barrett Technology"]], [["obj", "http://www.wikidata.org/entity/Q6647356"], ["uni", "Lit Motors"]], [["obj", "http://www.wikidata.org/entity/Q359"], ["uni", "WikiLeaks"]], [["obj", "http://www.wikidata.org/entity/Q317087"], ["uni", "University of L\u00fcbeck"]], [["obj", "http://www.wikidata.org/entity/Q2304477"], ["uni", "South East European University"]], [["obj", "http://www.wikidata.org/entity/Q2303478"], ["uni", "Synopsys"]], [["obj", "http://www.wikidata.org/entity/Q11838090"], ["uni", "Faculty of Mathematics and Computer Science of Jagiellonian University"]], [["obj", "http://www.wikidata.org/entity/Q1681557"], ["uni", "Junta para Ampliaci\u00f3n de Estudios"]], [["obj", "http://www.wikidata.org/entity/Q195046"], ["uni", "Worcester Polytechnic Institute"]], [["obj", "http://www.wikidata.org/entity/Q3272069"], ["uni", "Art Center College of Design"]], [["obj", "http://www.wikidata.org/entity/Q49087"], ["uni", "Fisk University"]], [["obj", "http://www.wikidata.org/entity/Q785697"], ["uni", "Shogakukan"]], [["obj", "http://www.wikidata.org/entity/Q863813"], ["uni", "Binghamton University"]], [["obj", "http://www.wikidata.org/entity/Q1117048"], ["uni", "Commonwealth Scientific and Industrial Research Organisation"]], [["obj", "http://www.wikidata.org/entity/Q587326"], ["uni", "Tokyo Institute of Technology"]], [["obj", "http://www.wikidata.org/entity/Q6360885"], ["uni", "Kanazawa Institute of Technology"]], [["obj", "http://www.wikidata.org/entity/Q7166356"], ["uni", "Pepper Hamilton"]]], "parseError": null, "execution": [{"datetime": "20/Dec/2022:21:24:36"}, {"datetime": "20/Dec/2022:21:34:15"}], "keywords": {"SELECT": 1, "ASK": 0, "DESCRIBE": 0, "CONSTRUCT": 0, "NESTED QUERY": 0, "DISTINCT": 1, "LIMIT": 1, "OFFSET": 0, "ORDER BY": 0, "FILTER": 0, "REGEX": 0, "AND": 0, "UNION": 0, "OPT": 0, "GRAPH": 0, "EXISTS": 0, "NOT EXISTS": 0, "MINUS": 0, "COUNT": 0, "MAX": 0, "MIN": 0, "AVG": 0, "SUM": 0, "GROUP BY": 0, "HAVING": 0, "GROUP_CONCAT": 0}, "index": 1, "recall": 0.0, "precision": 0.0, "accuracy": 0.0, "fscore": 0.0}, {"narrative": "[('obj', 'http://www.wikidata.org/entity/Q35794'), ('uni', 'University of Cambridge')\n[('obj', 'http://www.wikidata.org/entity/Q1622272'), ('name', 'university teacher')]\n[('obj', 'http://www.wikidata.org/entity/Q82594'), ('name', 'computer scientist')]\nFind all the computer scientists who thaught at the University of Cambridge (return IRI and name) (this query has been written considering both university teacher\nand computer scientist as occupation)", "query": "SELECT DISTINCT ?computer_scientist ?name WHERE { ?computer_scientist wdt:P31 wd:Q5; wdt:P108 wd:Q35794; wdt:P106 wd:Q1622272; wdt:P106 wd:Q82594. ?computer_scientist sc:name ?name. } LIMIT 20", "output": [[["computer_scientist", "http://www.wikidata.org/entity/Q46633"], ["name", "Charles Babbage"]], [["computer_scientist", "http://www.wikidata.org/entity/Q62857"], ["name", "Maurice Wilkes"]], [["computer_scientist", "http://www.wikidata.org/entity/Q451770"], ["name", "Douglas Hartree"]], [["computer_scientist", "http://www.wikidata.org/entity/Q4707402"], ["name", "Alan Mycroft"]], [["computer_scientist", "http://www.wikidata.org/entity/Q63126308"], ["name", "Peter F\u00f6ldi\u00e1k"]], [["computer_scientist", "http://www.wikidata.org/entity/Q216811"], ["name", "John Venn"]], [["computer_scientist", "http://www.wikidata.org/entity/Q100586732"], ["name", "Ferenc Husz\u00e1r"]], [["computer_scientist", "http://www.wikidata.org/entity/Q316330"], ["name", "Daniel Bell"]]], "parseError": null, "execution": [{"datetime": "20/Dec/2022:21:36:01"}, {"datetime": "20/Dec/2022:21:39:57"}], "keywords": {"SELECT": 1, "ASK": 0, "DESCRIBE": 0, "CONSTRUCT": 0, "NESTED QUERY": 0, "DISTINCT": 1, "LIMIT": 1, "OFFSET": 0, "ORDER BY": 0, "FILTER": 0, "REGEX": 0, "AND": 0, "UNION": 0, "OPT": 0, "GRAPH": 0, "EXISTS": 0, "NOT EXISTS": 0, "MINUS": 0, "COUNT": 0, "MAX": 0, "MIN": 0, "AVG": 0, "SUM": 0, "GROUP BY": 0, "HAVING": 0, "GROUP_CONCAT": 0}, "index": 2, "recall": 0.2222222222222222, "precision": 1.0, "accuracy": 0.0, "fscore": 0.3636363636363636}], "7": [{"narrative": "let's get the old query that gets all the computer scientists", "query": "SELECT DISTINCT ?computer_scientist ?name WHERE { ?computer_scientist wdt:P31 wd:Q5; wdt:P106 wd:Q82594. ?computer_scientist sc:name ?name. } LIMIT 20", "output": [[["computer_scientist", "http://www.wikidata.org/entity/Q8190500"], ["name", "Seinosuke Toda"]], [["computer_scientist", "http://www.wikidata.org/entity/Q603999"], ["name", "Kevin Poulsen"]], [["computer_scientist", "http://www.wikidata.org/entity/Q11109023"], ["name", "Michael Barr"]], [["computer_scientist", "http://www.wikidata.org/entity/Q20731777"], ["name", "Valeria de Paiva"]], [["computer_scientist", "http://www.wikidata.org/entity/Q24901829"], ["name", "Ernesto Damiani"]], [["computer_scientist", "http://www.wikidata.org/entity/Q61856956"], ["name", "Richard Garner"]], [["computer_scientist", "http://www.wikidata.org/entity/Q6539960"], ["name", "Liang-Jie Zhang"]], [["computer_scientist", "http://www.wikidata.org/entity/Q92669"], ["name", "Jeffrey Shallit"]], [["computer_scientist", "http://www.wikidata.org/entity/Q15842362"], ["name", "Richard Clippinger"]], [["computer_scientist", "http://www.wikidata.org/entity/Q15858435"], ["name", "Hardo Bourguignon"]], [["computer_scientist", "http://www.wikidata.org/entity/Q15917430"], ["name", "A. Ollongren"]], [["computer_scientist", "http://www.wikidata.org/entity/Q16018928"], ["name", "Jim Thomas"]], [["computer_scientist", "http://www.wikidata.org/entity/Q241735"], ["name", "Robert Noyce"]], [["computer_scientist", "http://www.wikidata.org/entity/Q7312654"], ["name", "Renato M. E. Sabbatini"]], [["computer_scientist", "http://www.wikidata.org/entity/Q16174254"], ["name", "Drude Berntsen"]], [["computer_scientist", "http://www.wikidata.org/entity/Q16186703"], ["name", "Timothy J. Hickey"]], [["computer_scientist", "http://www.wikidata.org/entity/Q16193458"], ["name", "Terry Myerson"]], [["computer_scientist", "http://www.wikidata.org/entity/Q16194868"], ["name", "Ross Williams"]], [["computer_scientist", "http://www.wikidata.org/entity/Q16195136"], ["name", "Frans Kaashoek"]], [["computer_scientist", "http://www.wikidata.org/entity/Q16195669"], ["name", "William Martens"]]], "parseError": null, "execution": [{"datetime": "20/Dec/2022:20:54:48"}, {"datetime": "20/Dec/2022:20:57:23"}, {"datetime": "20/Dec/2022:21:16:04"}, {"datetime": "20/Dec/2022:21:40:41"}], "keywords": {"SELECT": 1, "ASK": 0, "DESCRIBE": 0, "CONSTRUCT": 0, "NESTED QUERY": 0, "DISTINCT": 1, "LIMIT": 1, "OFFSET": 0, "ORDER BY": 0, "FILTER": 0, "REGEX": 0, "AND": 0, "UNION": 0, "OPT": 0, "GRAPH": 0, "EXISTS": 0, "NOT EXISTS": 0, "MINUS": 0, "COUNT": 0, "MAX": 0, "MIN": 0, "AVG": 0, "SUM": 0, "GROUP BY": 0, "HAVING": 0, "GROUP_CONCAT": 0}, "index": 0}, {"narrative": "", "query": "SELECT DISTINCT ?obj ?name WHERE { wd:Q316330 wdt:P106 ?obj. ?obj sc:name ?name. } LIMIT 20", "output": [[["obj", "http://www.wikidata.org/entity/Q1622272"], ["name", "university teacher"]], [["obj", "http://www.wikidata.org/entity/Q1930187"], ["name", "journalist"]], [["obj", "http://www.wikidata.org/entity/Q36180"], ["name", "writer"]], [["obj", "http://www.wikidata.org/entity/Q37226"], ["name", "teacher"]], [["obj", "http://www.wikidata.org/entity/Q82594"], ["name", "computer scientist"]], [["obj", "http://www.wikidata.org/entity/Q2306091"], ["name", "sociologist"]], [["obj", "http://www.wikidata.org/entity/Q6051619"], ["name", "opinion journalist"]]], "parseError": null, "execution": [{"datetime": "20/Dec/2022:23:14:47"}, {"datetime": "20/Dec/2022:23:14:47"}], "keywords": {"SELECT": 1, "ASK": 0, "DESCRIBE": 0, "CONSTRUCT": 0, "NESTED QUERY": 0, "DISTINCT": 1, "LIMIT": 1, "OFFSET": 0, "ORDER BY": 0, "FILTER": 0, "REGEX": 0, "AND": 0, "UNION": 0, "OPT": 0, "GRAPH": 0, "EXISTS": 0, "NOT EXISTS": 0, "MINUS": 0, "COUNT": 0, "MAX": 0, "MIN": 0, "AVG": 0, "SUM": 0, "GROUP BY": 0, "HAVING": 0, "GROUP_CONCAT": 0}, "index": 1}, {"narrative": "[('obj', 'http://www.wikidata.org/entity/Q36180'), ('name', 'writer')]", "query": "SELECT DISTINCT ?p ?name WHERE { wd:Q36180 ?b ?p. ?p sc:name ?name. } LIMIT 50", "output": [[["p", "http://www.wikidata.org/entity/Q37260"], ["name", "writing"]], [["p", "http://www.wikidata.org/entity/Q2250012"], ["name", "writing"]], [["p", "http://www.wikidata.org/entity/Q5849863"], ["name", "Category:Writers"]], [["p", "http://www.wikidata.org/entity/P50"], ["name", "author"]], [["p", "http://www.wikidata.org/entity/Q12737077"], ["name", "occupation"]], [["p", "http://www.wikidata.org/entity/Q28640"], ["name", "profession"]], [["p", "http://www.wikidata.org/entity/Q4164871"], ["name", "position"]], [["p", "http://www.wikidata.org/entity/Q482980"], ["name", "author"]], [["p", "http://www.wikidata.org/entity/Q98970039"], ["name", "WikiProject PCC Wikidata Pilot/University of Washington"]], [["p", "http://www.wikidata.org/entity/Q13019738"], ["name", "list of lists of writers"]], [["p", "http://www.wikidata.org/entity/Q6963972"], ["name", "Category:Wikipedia categories named after writers"]], [["p", "http://www.wikidata.org/entity/P2093"], ["name", "author name string"]], [["p", "http://www.wikidata.org/entity/Q5615832"], ["name", "Template:Infobox writer"]], [["p", "http://www.wikidata.org/entity/Q6535605"], ["name", "Template:Writer-stub"]]], "parseError": null, "execution": [{"datetime": "20/Dec/2022:23:19:18"}], "keywords": {"SELECT": 1, "ASK": 0, "DESCRIBE": 0, "CONSTRUCT": 0, "NESTED QUERY": 0, "DISTINCT": 1, "LIMIT": 1, "OFFSET": 0, "ORDER BY": 0, "FILTER": 0, "REGEX": 0, "AND": 0, "UNION": 0, "OPT": 0, "GRAPH": 0, "EXISTS": 0, "NOT EXISTS": 0, "MINUS": 0, "COUNT": 0, "MAX": 0, "MIN": 0, "AVG": 0, "SUM": 0, "GROUP BY": 0, "HAVING": 0, "GROUP_CONCAT": 0}, "index": 2}, {"narrative": "[('p', 'http://www.wikidata.org/entity/P50'), ('name', 'author')]", "query": "SELECT DISTINCT ?job ?name WHERE { wd:Q482980 ?b ?job. ?job sc:name ?name. } LIMIT 20", "output": [[["job", "http://www.wikidata.org/entity/Q9701158"], ["name", "Category:Authors"]], [["job", "http://www.wikidata.org/entity/P50"], ["name", "author"]], [["job", "http://www.wikidata.org/entity/P3931"], ["name", "copyright holder"]], [["job", "http://www.wikidata.org/entity/Q12737077"], ["name", "occupation"]], [["job", "http://www.wikidata.org/entity/Q42"], ["name", "Douglas Adams"]], [["job", "http://www.wikidata.org/entity/Q692"], ["name", "William Shakespeare"]], [["job", "http://www.wikidata.org/entity/Q8209871"], ["name", "Autor"]], [["job", "http://www.wikidata.org/entity/P170"], ["name", "creator"]], [["job", "http://www.wikidata.org/entity/Q2500638"], ["name", "creator"]], [["job", "http://www.wikidata.org/entity/Q8347428"], ["name", "Category:Categories by writer"]], [["job", "http://www.wikidata.org/entity/Q10859333"], ["name", "authorship"]], [["job", "http://www.wikidata.org/entity/Q36322"], ["name", "Jane Austen"]], [["job", "http://www.wikidata.org/entity/P1778"], ["name", "forgery after"]]], "parseError": null, "execution": [{"datetime": "20/Dec/2022:23:20:53"}], "keywords": {"SELECT": 1, "ASK": 0, "DESCRIBE": 0, "CONSTRUCT": 0, "NESTED QUERY": 0, "DISTINCT": 1, "LIMIT": 1, "OFFSET": 0, "ORDER BY": 0, "FILTER": 0, "REGEX": 0, "AND": 0, "UNION": 0, "OPT": 0, "GRAPH": 0, "EXISTS": 0, "NOT EXISTS": 0, "MINUS": 0, "COUNT": 0, "MAX": 0, "MIN": 0, "AVG": 0, "SUM": 0, "GROUP BY": 0, "HAVING": 0, "GROUP_CONCAT": 0}, "index": 3}, {"narrative": "", "query": "SELECT DISTINCT ?job ?name WHERE { wd:Q692 ?b ?job. ?job sc:name ?name. } LIMIT 20", "output": [[["job", "http://www.wikidata.org/entity/Q662550"], ["name", "Shakespeare's sonnets"]], [["job", "http://www.wikidata.org/entity/Q661222"], ["name", "King John"]], [["job", "http://www.wikidata.org/entity/Q215750"], ["name", "Julius Caesar"]], [["job", "http://www.wikidata.org/entity/Q38933"], ["name", "fever"]], [["job", "http://www.wikidata.org/entity/Q53590"], ["name", "The Two Noble Kinsmen"]], [["job", "http://www.wikidata.org/entity/Q128610"], ["name", "Love's Labour's Lost"]], [["job", "http://www.wikidata.org/entity/Q130283"], ["name", "Macbeth"]], [["job", "http://www.wikidata.org/entity/Q181598"], ["name", "King Lear"]], [["job", "http://www.wikidata.org/entity/Q332387"], ["name", "The Taming of the Shrew"]], [["job", "http://www.wikidata.org/entity/Q83186"], ["name", "Romeo and Juliet"]], [["job", "http://www.wikidata.org/entity/Q506505"], ["name", "The Comedy of Errors"]], [["job", "http://www.wikidata.org/entity/Q64759522"], ["name", "Star Trek Concordance"]], [["job", "http://www.wikidata.org/entity/Q221211"], ["name", "Twelfth Night"]], [["job", "http://www.wikidata.org/entity/Q86440"], ["name", "The Tempest"]], [["job", "http://www.wikidata.org/entity/Q106727050"], ["name", "Metropolitan Museum of Art Tagging Vocabulary"]], [["job", "http://www.wikidata.org/entity/Q12344159"], ["name", "William"]], [["job", "http://www.wikidata.org/entity/Q15987216"], ["name", "Dictionary of National Biography, 1885\u20131900"]], [["job", "http://www.wikidata.org/entity/Q1700481"], ["name", "Minneapolis Institute of Art"]], [["job", "http://www.wikidata.org/entity/Q17378135"], ["name", "Great Soviet Encyclopedia (1969\u20131978)"]], [["job", "http://www.wikidata.org/entity/Q179876"], ["name", "Kingdom of England"]]], "parseError": null, "execution": [{"datetime": "20/Dec/2022:23:21:38"}, {"datetime": "20/Dec/2022:23:23:16"}], "keywords": {"SELECT": 1, "ASK": 0, "DESCRIBE": 0, "CONSTRUCT": 0, "NESTED QUERY": 0, "DISTINCT": 1, "LIMIT": 1, "OFFSET": 0, "ORDER BY": 0, "FILTER": 0, "REGEX": 0, "AND": 0, "UNION": 0, "OPT": 0, "GRAPH": 0, "EXISTS": 0, "NOT EXISTS": 0, "MINUS": 0, "COUNT": 0, "MAX": 0, "MIN": 0, "AVG": 0, "SUM": 0, "GROUP BY": 0, "HAVING": 0, "GROUP_CONCAT": 0}, "index": 4}, {"narrative": "", "query": "SELECT DISTINCT ?job ?name WHERE { wd:Q83186 ?b ?job. ?job sc:name ?name. } LIMIT 10", "output": [[["job", "http://www.wikidata.org/entity/Q673361"], ["name", "Romeo"]], [["job", "http://www.wikidata.org/entity/Q911487"], ["name", "Romeo and Juliet"]], [["job", "http://www.wikidata.org/entity/Q19968309"], ["name", "Romeo and Juliet"]], [["job", "http://www.wikidata.org/entity/Q25379"], ["name", "play"]], [["job", "http://www.wikidata.org/entity/Q191489"], ["name", "melodrama"]], [["job", "http://www.wikidata.org/entity/Q1071307"], ["name", "I Capuleti e i Montecchi"]], [["job", "http://www.wikidata.org/entity/Q179876"], ["name", "Kingdom of England"]], [["job", "http://www.wikidata.org/entity/Q1860"], ["name", "English"]], [["job", "http://www.wikidata.org/entity/Q19652"], ["name", "public domain"]], [["job", "http://www.wikidata.org/entity/Q2028"], ["name", "Verona"]]], "parseError": null, "execution": [{"datetime": "20/Dec/2022:23:22:43"}, {"datetime": "20/Dec/2022:23:28:28"}], "keywords": {"SELECT": 1, "ASK": 0, "DESCRIBE": 0, "CONSTRUCT": 0, "NESTED QUERY": 0, "DISTINCT": 1, "LIMIT": 1, "OFFSET": 0, "ORDER BY": 0, "FILTER": 0, "REGEX": 0, "AND": 0, "UNION": 0, "OPT": 0, "GRAPH": 0, "EXISTS": 0, "NOT EXISTS": 0, "MINUS": 0, "COUNT": 0, "MAX": 0, "MIN": 0, "AVG": 0, "SUM": 0, "GROUP BY": 0, "HAVING": 0, "GROUP_CONCAT": 0}, "index": 5}, {"narrative": "", "query": "SELECT DISTINCT ?job ?name WHERE { wd:Q83186 ?b ?job. ?job sc:name ?name. } LIMIT 100", "output": [[["job", "http://www.wikidata.org/entity/Q673361"], ["name", "Romeo"]], [["job", "http://www.wikidata.org/entity/Q911487"], ["name", "Romeo and Juliet"]], [["job", "http://www.wikidata.org/entity/Q19968309"], ["name", "Romeo and Juliet"]], [["job", "http://www.wikidata.org/entity/Q25379"], ["name", "play"]], [["job", "http://www.wikidata.org/entity/Q191489"], ["name", "melodrama"]], [["job", "http://www.wikidata.org/entity/Q1071307"], ["name", "I Capuleti e i Montecchi"]], [["job", "http://www.wikidata.org/entity/Q179876"], ["name", "Kingdom of England"]], [["job", "http://www.wikidata.org/entity/Q1860"], ["name", "English"]], [["job", "http://www.wikidata.org/entity/Q19652"], ["name", "public domain"]], [["job", "http://www.wikidata.org/entity/Q2028"], ["name", "Verona"]], [["job", "http://www.wikidata.org/entity/Q6247"], ["name", "Mantua"]], [["job", "http://www.wikidata.org/entity/Q7725634"], ["name", "literary work"]], [["job", "http://www.wikidata.org/entity/Q80930"], ["name", "tragedy"]], [["job", "http://www.wikidata.org/entity/Q692"], ["name", "William Shakespeare"]], [["job", "http://www.wikidata.org/entity/Q191803"], ["name", "The Lion King II: Simba's Pride"]], [["job", "http://www.wikidata.org/entity/Q1670602"], ["name", "Rom\u00e9o et Juliette, de la Haine \u00e0 l'Amour"]], [["job", "http://www.wikidata.org/entity/Q463313"], ["name", "Romeo + Juliet"]], [["job", "http://www.wikidata.org/entity/Q1092632"], ["name", "Juliet"]], [["job", "http://www.wikidata.org/entity/Q7600519"], ["name", "star-crossed lovers"]], [["job", "http://www.wikidata.org/entity/Q2165127"], ["name", "Romeo und Julia"]], [["job", "http://www.wikidata.org/entity/Q56150619"], ["name", "The tragedie of Romeo and Juliet"]], [["job", "http://www.wikidata.org/entity/Q58894671"], ["name", "Romaios kai Ioulieta"]], [["job", "http://www.wikidata.org/entity/Q1767900"], ["name", "Mercutio"]], [["job", "http://www.wikidata.org/entity/Q77103486"], ["name", "RJ Romeo and Juliet"]], [["job", "http://www.wikidata.org/entity/Q47509134"], ["name", "Julia"]], [["job", "http://www.wikidata.org/entity/Q918714"], ["name", "Rom\u00e9o et Juliette"]], [["job", "http://www.wikidata.org/entity/Q1158741"], ["name", "Tromeo and Juliet"]], [["job", "http://www.wikidata.org/entity/Q5139014"], ["name", "Make Your Move"]], [["job", "http://www.wikidata.org/entity/Q24904727"], ["name", "Sherlock Gnomes"]], [["job", "http://www.wikidata.org/entity/Q753677"], ["name", "Gnomeo & Juliet"]], [["job", "http://www.wikidata.org/entity/Q3404244"], ["name", "Private Romeo"]], [["job", "http://www.wikidata.org/entity/Q3940834"], ["name", "Romeo and Juliet"]], [["job", "http://www.wikidata.org/entity/Q939489"], ["name", "Benvolio"]], [["job", "http://www.wikidata.org/entity/Q101095685"], ["name", "What if Romeo & Juliet\u2026"]], [["job", "http://www.wikidata.org/entity/Q1081181"], ["name", "Romeo and Juliet"]], [["job", "http://www.wikidata.org/entity/Q1251572"], ["name", "Romeo and Juliet: the Tomb Scene"]], [["job", "http://www.wikidata.org/entity/Q1491432"], ["name", "56 csepp v\u00e9r"]], [["job", "http://www.wikidata.org/entity/Q1758089"], ["name", "Romeo and Juliet"]], [["job", "http://www.wikidata.org/entity/Q19101009"], ["name", "The Tragedy of Romeo and Juliet"]], [["job", "http://www.wikidata.org/entity/Q19101569"], ["name", "Romeo and Juliet"]], [["job", "http://www.wikidata.org/entity/Q19225891"], ["name", "Romeo und Juliette"]], [["job", "http://www.wikidata.org/entity/Q20649699"], ["name", "Romeo and Juliet"]], [["job", "http://www.wikidata.org/entity/Q223857"], ["name", "Romeo and Juliet"]], [["job", "http://www.wikidata.org/entity/Q23301380"], ["name", "The Tragedy of Romeo and Juliet"]], [["job", "http://www.wikidata.org/entity/Q2412073"], ["name", "Tybalt"]], [["job", "http://www.wikidata.org/entity/Q2716956"], ["name", "Romeo and Juliet"]], [["job", "http://www.wikidata.org/entity/Q28761773"], ["name", "Rom\u00e9o et Juliette"]], [["job", "http://www.wikidata.org/entity/Q28938633"], ["name", "Rom\u00e9o et Juliette"]], [["job", "http://www.wikidata.org/entity/Q3441351"], ["name", "Romeo and Juliet"]], [["job", "http://www.wikidata.org/entity/Q47435665"], ["name", "Romeo und Julia"]], [["job", "http://www.wikidata.org/entity/Q517265"], ["name", "Romeo and Juliet"]], [["job", "http://www.wikidata.org/entity/Q531630"], ["name", "La tr\u00e1gica historia de Romeo y Julieta"]], [["job", "http://www.wikidata.org/entity/Q55839872"], ["name", "Romeo and Juliet"]], [["job", "http://www.wikidata.org/entity/Q58894270"], ["name", "\u0420\u043e\u043c\u0435\u043e \u0438 \u0408\u0443\u043b\u0438\u0458\u0430"]], [["job", "http://www.wikidata.org/entity/Q58894719"], ["name", "Romeo y Julieta"]], [["job", "http://www.wikidata.org/entity/Q58894744"], ["name", "Romeo \u00e9s J\u00falia"]], [["job", "http://www.wikidata.org/entity/Q58894783"], ["name", "Romeo \u0219i Julieta"]], [["job", "http://www.wikidata.org/entity/Q58896230"], ["name", "Romeo i Julia"]], [["job", "http://www.wikidata.org/entity/Q58897332"], ["name", "Romeo und Julia"]], [["job", "http://www.wikidata.org/entity/Q58897522"], ["name", "Romeu i Julieta"]], [["job", "http://www.wikidata.org/entity/Q62656523"], ["name", "The Most Excellent and Lamentable Tragedy of Romeo and Juliet"]], [["job", "http://www.wikidata.org/entity/Q6398196"], ["name", "Category:Romeo and Juliet"]], [["job", "http://www.wikidata.org/entity/Q763716"], ["name", "Romeo and Juliet"]]], "parseError": null, "execution": [{"datetime": "20/Dec/2022:23:22:55"}, {"datetime": "20/Dec/2022:23:43:22"}], "keywords": {"SELECT": 1, "ASK": 0, "DESCRIBE": 0, "CONSTRUCT": 0, "NESTED QUERY": 0, "DISTINCT": 1, "LIMIT": 1, "OFFSET": 0, "ORDER BY": 0, "FILTER": 0, "REGEX": 0, "AND": 0, "UNION": 0, "OPT": 0, "GRAPH": 0, "EXISTS": 0, "NOT EXISTS": 0, "MINUS": 0, "COUNT": 0, "MAX": 0, "MIN": 0, "AVG": 0, "SUM": 0, "GROUP BY": 0, "HAVING": 0, "GROUP_CONCAT": 0}, "index": 6}, {"narrative": "", "query": "SELECT DISTINCT ?job ?name WHERE { wd:Q7725634 ?b ?job. ?job sc:name ?name. } LIMIT 100", "output": [[["job", "http://www.wikidata.org/entity/P747"], ["name", "has edition or translation"]], [["job", "http://www.wikidata.org/entity/Q3919906"], ["name", "Category:Literary works"]], [["job", "http://www.wikidata.org/entity/P214"], ["name", "VIAF ID"]], [["job", "http://www.wikidata.org/entity/Q234460"], ["name", "text"]], [["job", "http://www.wikidata.org/entity/P373"], ["name", "Commons category"]], [["job", "http://www.wikidata.org/entity/P123"], ["name", "publisher"]], [["job", "http://www.wikidata.org/entity/P407"], ["name", "language of work or name"]], [["job", "http://www.wikidata.org/entity/P50"], ["name", "author"]], [["job", "http://www.wikidata.org/entity/P921"], ["name", "main subject"]], [["job", "http://www.wikidata.org/entity/Q47461344"], ["name", "written work"]], [["job", "http://www.wikidata.org/entity/Q8242"], ["name", "literature"]], [["job", "http://www.wikidata.org/entity/Q3331189"], ["name", "version, edition, or translation"]], [["job", "http://www.wikidata.org/entity/P577"], ["name", "publication date"]], [["job", "http://www.wikidata.org/entity/P495"], ["name", "country of origin"]], [["job", "http://www.wikidata.org/entity/P227"], ["name", "GND ID"]], [["job", "http://www.wikidata.org/entity/Q838948"], ["name", "work of art"]], [["job", "http://www.wikidata.org/entity/Q315"], ["name", "language"]], [["job", "http://www.wikidata.org/entity/P136"], ["name", "genre"]], [["job", "http://www.wikidata.org/entity/P2408"], ["name", "set in period"]], [["job", "http://www.wikidata.org/entity/P840"], ["name", "narrative location"]], [["job", "http://www.wikidata.org/entity/P166"], ["name", "award received"]], [["job", "http://www.wikidata.org/entity/P7937"], ["name", "form of creative work"]], [["job", "http://www.wikidata.org/entity/Q16537202"], ["name", "list of literary works"]], [["job", "http://www.wikidata.org/entity/P949"], ["name", "National Library of Israel ID"]], [["job", "http://www.wikidata.org/entity/Q8487081"], ["name", "WikiProject Books"]], [["job", "http://www.wikidata.org/entity/Q14191166"], ["name", "Template:Infobox literary work"]], [["job", "http://www.wikidata.org/entity/Q8104190"], ["name", "Category:Wikipedia categories named after literary texts"]]], "parseError": null, "execution": [{"datetime": "20/Dec/2022:23:25:31"}, {"datetime": "20/Dec/2022:23:43:46"}], "keywords": {"SELECT": 1, "ASK": 0, "DESCRIBE": 0, "CONSTRUCT": 0, "NESTED QUERY": 0, "DISTINCT": 1, "LIMIT": 1, "OFFSET": 0, "ORDER BY": 0, "FILTER": 0, "REGEX": 0, "AND": 0, "UNION": 0, "OPT": 0, "GRAPH": 0, "EXISTS": 0, "NOT EXISTS": 0, "MINUS": 0, "COUNT": 0, "MAX": 0, "MIN": 0, "AVG": 0, "SUM": 0, "GROUP BY": 0, "HAVING": 0, "GROUP_CONCAT": 0}, "index": 7}]}}